{
    "-1911724038": {
        "editor_type": "ability_all", 
        "index_type": "object_editor", 
        "item_key": 134270288, 
        "prop_key": "name"
    }, 
    "-1546708137": {
        "editor_type": "modifier_all", 
        "index_type": "object_editor", 
        "item_key": 134226052, 
        "prop_key": "name"
    }, 
    "-1443008480": {
        "editor_type": "ability_all", 
        "index_type": "object_editor", 
        "item_key": 134279288, 
        "prop_key": "name"
    }, 
    "-1400675901": {
        "editor_type": "projectile_all", 
        "index_type": "object_editor", 
        "item_key": 134270690, 
        "prop_key": "desc"
    }, 
    "-998767957": {
        "editor_type": "projectile_all", 
        "index_type": "object_editor", 
        "item_key": 134270690, 
        "prop_key": "name"
    }, 
    "-842605453": {
        "editor_type": "modifier_all", 
        "index_type": "object_editor", 
        "item_key": 134280151, 
        "prop_key": "name"
    }, 
    "-635403917": {
        "editor_type": "editor_unit", 
        "index_type": "object_editor", 
        "item_key": 134249471, 
        "prop_key": "name"
    }, 
    "-44460504": {
        "editor_type": "ability_all", 
        "index_type": "object_editor", 
        "item_key": 134224183, 
        "prop_key": "name"
    }, 
    "423794095": {
        "editor_type": "editor_unit", 
        "index_type": "object_editor", 
        "item_key": 134217907, 
        "prop_key": "desc"
    }, 
    "444007242": {
        "editor_type": "ability_all", 
        "index_type": "object_editor", 
        "item_key": 134224183, 
        "prop_key": "desc"
    }, 
    "986124904": {
        "editor_type": "modifier_all", 
        "index_type": "object_editor", 
        "item_key": 134244797, 
        "prop_key": "name"
    }, 
    "1229344442": {
        "editor_type": "ability_all", 
        "index_type": "object_editor", 
        "item_key": 134279288, 
        "prop_key": "desc"
    }, 
    "1715737100": {
        "editor_type": "editor_unit", 
        "index_type": "object_editor", 
        "item_key": 134276028, 
        "prop_key": "desc"
    }, 
    "1752757959": {
        "editor_type": "editor_unit", 
        "index_type": "object_editor", 
        "item_key": 134276028, 
        "prop_key": "name"
    }
}